cryopy/__init__.py
cryopy/constant.py
cryopy/flow.py
cryopy/convert/__init__.py
cryopy/convert/volume.py
cryopy/function/HeatTransfert.py
cryopy/function/ThermalConductivity.py
cryopy/function/__init__.py
cryopy/function/electronics.py
cryopy/function/flow.py
cryopy/helium/__init__.py
cryopy/helium/fermi.py
cryopy/helium/helium3.py
cryopy/helium/helium4.py
cryopy/helium/helium4_sandbox.py
cryopy/helium/helium7.py
cryopy/helium/helium3/__init__.py
cryopy/helium/helium3/dynamic_viscosity/__init__.py
cryopy/helium/helium3/dynamic_viscosity/function.py
cryopy/instrument/__init__.py
cryopy/instrument/alcatel/__init__.py
cryopy/instrument/alcatel/asm142.py
cryopy/instrument/cryocon/__init__.py
cryopy/instrument/cryocon/model54.py
cryopy/instrument/fluke/__init__.py
cryopy/instrument/fluke/fluke8842a.py
cryopy/instrument/keithley/__init__.py
cryopy/instrument/keithley/keithley192.py
cryopy/instrument/keithley/keithley196.py
cryopy/instrument/keithley/keithley2000.py
cryopy/instrument/keithley/keithley2602.py
cryopy/instrument/lakeshore/__init__.py
cryopy/instrument/lakeshore/lakeshore336.py
cryopy/instrument/lakeshore/lakeshore370.py
cryopy/instrument/lakeshore/lakeshore372.py
cryopy/instrument/tti/__init__.py
cryopy/instrument/tti/qi355tp.py
cryopy/instrument/yokogawa/__init__.py
cryopy/instrument/yokogawa/yokogawa7562.py
cryopy/material/Al6061_T6.py
cryopy/material/Cu_OFHC.py
cryopy/material/__init__.py
cryopy/material/untitled6.py
cryopy/material/sandbox/Al1100.py
cryopy/material/sandbox/Al3003_F.py
cryopy/material/sandbox/Al5083_O.py
cryopy/material/sandbox/Al6063_T5.py
cryopy/material/sandbox/Apiezon_N.py
cryopy/material/sandbox/Be.py
cryopy/material/sandbox/Cu.py
cryopy/material/sandbox/Cu46Ni13Zn41.py
cryopy/material/sandbox/Cu60Ni40.py
cryopy/material/sandbox/Cu64Ni16Zn20.py
cryopy/material/sandbox/Cu66Zn34.py
cryopy/material/sandbox/Cu70Ni30.py
cryopy/material/sandbox/Cu80Ni20.py
cryopy/material/sandbox/Cu84Ni4Mn12.py
cryopy/material/sandbox/CuBe.py
cryopy-0.0.80.dist-info/licenses/LICENSE
cryopy-0.0.80.dist-info/METADATA
cryopy-0.0.80.dist-info/WHEEL
cryopy-0.0.80.dist-info/top_level.txt
cryopy-0.0.80.dist-info/RECORD
