Metadata-Version: 2.4
Name: cryopy
Version: 0.0.80
Summary: This package gather many useful datas for cryogenic
Home-page: https://github.com/pypa/sampleproject
Author: Valentin SAUVAGE
Author-email: valentin.sauvage@outlook.com
Project-URL: Bug Tracker, https://github.com/pypa/sampleproject/issues
Classifier: Programming Language :: Python :: 3
Classifier: License :: OSI Approved :: MIT License
Classifier: Operating System :: OS Independent
Requires-Python: >=3.6
License-File: LICENSE
Dynamic: license-file
